whelk/__init__.py
whelk-3.0.dist-info/COPYING
whelk-3.0.dist-info/METADATA
whelk-3.0.dist-info/WHEEL
whelk-3.0.dist-info/top_level.txt
whelk-3.0.dist-info/RECORD
